MANIFEST.in
README.rst
requirements.txt
setup.py
test-requirements.txt
config/__init__.py
config/config.py
config/version
py_config.egg-info/PKG-INFO
py_config.egg-info/SOURCES.txt
py_config.egg-info/dependency_links.txt
py_config.egg-info/requires.txt
py_config.egg-info/top_level.txt